<?xml version="1.0"?>

<jetAnalysis>

  <mode>0</mode>  <!-- 0: w/ combine, 1: w/o combine, 2: only combine-->
  <subtractionMethod>NaiveNegativeSub</subtractionMethod>

  <!-- Jet Reconstruction-->
  <jetReco>
    <reconstructionMethod>NegativeReco</reconstructionMethod>
    <jetR>
      <Item>0.3</Item>
    </jetR>
    <chJet>0</chJet>    <!-- 0: full jet, 1: charged jet -->

    <jetRapidity>1</jetRapidity>    <!-- 0: rapidity(Y), 1: pseudorapidity(Eta) -->
    <jetRapMin>
      <Item>0</Item>
    </jetRapMin>
    <jetRapMax>
      <Item>1.6</Item>
    </jetRapMax>
    <jetPtMin>
      <Item>30.0</Item>
    </jetPtMin>
    <jetPtMax>
      <Item>10000</Item>
    </jetPtMax>
    <nJetEv>0</nJetEv>    <!-- <= 0: inclusive -->
  </jetReco>

  <jetTag>
    <tagged>1</tagged>
    <xJetTag>0</xJetTag>    <!-- 1: jet triggered by momentum fraction Xjtag instead of pTjet-->
    <nTagEv>1</nTagEv>    <!-- 0: inclusive, 1: Highest pt in each event (leading: CMS) -->
    <!-- tag basic iinfo -->
    <tagParticle>
      <Item>22</Item>
    </tagParticle>
    <tagStat>
      <Item>0</Item>
      <Item>1</Item>
    </tagStat>
    <!-- tag pt cut -->
    <tagPtMin>100.0</tagPtMin>
    <tagPtMax>10000.0</tagPtMax>
    <!-- tag rapidity cut -->
    <tagRapidity>1</tagRapidity>    <!-- 0: rapidity(Y), 1: pseudorapidity(Eta) -->
    <tagRapMin>0</tagRapMin>
    <tagRapMax>1.44</tagRapMax>
    <!-- tag isolation -->
    <isolation>1</isolation>
    <RIsolation>0.4</RIsolation>
    <cutIsolation>5</cutIsolation>
    <varIsolation>pT</varIsolation>    <!-- pT, PT, Pt, pt: transverse momentum   ET, et, Et, eT: transverse energy -->
    <!-- <chIsolation>1</chIsolation>   -->
    <statIsolation>
      <Item>0</Item>
      <Item>1</Item>
      <Item>-1</Item>
    </statIsolation>
    <!-- tag relative angle -->
    <deltaPhiCut>1</deltaPhiCut>
    <deltaPhiMin>-0.875</deltaPhiMin>    <!-- negative value: to be multiplied by pi, 7/8 = 0.875-->
  </jetTag>

  <smearing>
    <method>CMSxJGamma</method>
    <C>0.06</C>
    <S>1.24</S>
    <N>0.0</N>
  </smearing>

  <observable>
    <MomFracTagJet>
      <smearing>1</smearing>
      <name>Transverse Momentum Fraction between Tag and Jet</name>
      <chParticle>0</chParticle>

      <particleRapidity>1</particleRapidity>
      <particleRapMin>
        <Item>0.0</Item>
      </particleRapMin>
      <particleRapMax>
        <Item>2.0</Item>
      </particleRapMax>
      <particlePtMin>
        <Item>0.0</Item>
      </particlePtMin>
      <particlePtMax>
        <Item>10000</Item>
      </particlePtMax>

      <var>
        <xJetTag>
          <Item>0.0</Item>
          <Item>0.125</Item>
          <Item>0.25</Item>
          <Item>0.375</Item>
          <Item>0.5</Item>
          <Item>0.625</Item>
          <Item>0.75</Item>
          <Item>0.875</Item>
          <Item>1.0</Item>
          <Item>1.125</Item>
          <Item>1.25</Item>
          <Item>1.375</Item>
          <Item>1.5</Item>
          <Item>1.625</Item>
          <Item>1.75</Item>
          <Item>1.875</Item>
          <Item>2.0</Item>
        </xJetTag>
      </var>

    </MomFracTagJet>


  </observable>

  <inputFiles>
    <inputStyle>JetScapeAscii</inputStyle>
    <events>
      <head>JetscapeHadronListBin</head>
      <join>_</join>
      <tail>.out</tail>
    </events>
    <sigma>
      <path>na</path>
      <head>SigmaHardBin</head>
      <join>_</join>
      <tail>.out</tail>
    </sigma>
    <divNum>0</divNum>    <!-- 0: default, 1-:  divided-->
    <divUnit>_Run</divUnit>
  </inputFiles>

  <!-- ptHatBins -->
  <ptHat>
    <Item>1</Item>
    <Item>2</Item>
    <Item>3</Item>
    <Item>4</Item>
    <Item>5</Item>
    <Item>7</Item>
    <Item>9</Item>
    <Item>11</Item>
    <Item>13</Item>
    <Item>15</Item>
    <Item>17</Item>
    <Item>20</Item>
    <Item>25</Item>
    <Item>30</Item>
    <Item>35</Item>
    <Item>40</Item>
    <Item>45</Item>
    <Item>50</Item>
    <Item>55</Item>
    <Item>60</Item>
    <Item>70</Item>
    <Item>80</Item>
    <Item>90</Item>
    <Item>100</Item>
    <Item>110</Item>
    <Item>120</Item>
    <Item>130</Item>
    <Item>140</Item>
    <Item>150</Item>
    <Item>160</Item>
    <Item>170</Item>
    <Item>180</Item>
    <Item>190</Item>
    <Item>200</Item>
    <Item>210</Item>
    <Item>220</Item>
    <Item>230</Item>
    <Item>240</Item>
    <Item>250</Item>
    <Item>260</Item>
    <Item>270</Item>
    <Item>280</Item>
    <Item>290</Item>
    <Item>300</Item>
    <Item>350</Item>
    <Item>400</Item>
    <Item>450</Item>
    <Item>500</Item>
    <Item>550</Item>
    <Item>600</Item>
    <Item>700</Item>
    <Item>800</Item>
    <Item>900</Item>
    <Item>1000</Item>
    <Item>1100</Item>
    <Item>1200</Item>
    <Item>1300</Item>
    <Item>1400</Item>
    <Item>1500</Item>
    <Item>1600</Item>
    <Item>1700</Item>
    <Item>1800</Item>
    <Item>1900</Item>
    <Item>2000</Item>
    <Item>2200</Item>
    <Item>2400</Item>
    <Item>2510</Item>
  </ptHat>

</jetAnalysis>
